JuMonC_LogParser/LogParser.py
JuMonC_LogParser/README.md
JuMonC_LogParser/_version.py
JuMonC_LogParser-0.1.0.dist-info/METADATA
JuMonC_LogParser-0.1.0.dist-info/WHEEL
JuMonC_LogParser-0.1.0.dist-info/entry_points.txt
JuMonC_LogParser-0.1.0.dist-info/top_level.txt
JuMonC_LogParser-0.1.0.dist-info/RECORD
