Metadata-Version: 2.1
Name: JuMonC-LogParser
Version: 0.1.0
Summary: LogParser plugin for JuMonC
Home-page: https://gitlab.jsc.fz-juelich.de/coec/jumonc-logparser
Author: Christian Witzler
Author-email: c.witzler@fz-juelich.de
License: BSD 3-Clause License
Classifier: License :: OSI Approved :: BSD License
Classifier: Programming Language :: Python :: 3
Classifier: Programming Language :: Python :: 3.9
Requires-Dist: JuMonC (>=0.8)
Requires-Dist: ply
